streamlit_imp_custom_model_history/__init__.py
streamlit_imp_custom_model_history/frontend/build/asset-manifest.json
streamlit_imp_custom_model_history/frontend/build/index.html
streamlit_imp_custom_model_history/frontend/build/static/css/main.96934b68.css
streamlit_imp_custom_model_history/frontend/build/static/css/main.96934b68.css.map
streamlit_imp_custom_model_history/frontend/build/static/js/main.06a25a9d.js
streamlit_imp_custom_model_history/frontend/build/static/js/main.06a25a9d.js.LICENSE.txt
streamlit_imp_custom_model_history/frontend/build/static/js/main.06a25a9d.js.map
streamlit_imp_custom_model_history/frontend/build/static/media/excel_file_icon.fc99a6556af7a636aa8d.png
streamlit_imp_custom_model_history/frontend/build/static/media/output.55931810b4d5a9916a27.png
streamlit_imp_custom_model_history-2.0.0.dist-info/LICENSE
streamlit_imp_custom_model_history-2.0.0.dist-info/METADATA
streamlit_imp_custom_model_history-2.0.0.dist-info/WHEEL
streamlit_imp_custom_model_history-2.0.0.dist-info/top_level.txt
streamlit_imp_custom_model_history-2.0.0.dist-info/RECORD
