Metadata-Version: 2.1
Name: streamlit-imp-custom-model-history
Version: 2.0.0
Summary: UNKNOWN
Home-page: UNKNOWN
Author: 
Author-email: 
License: UNKNOWN
Platform: UNKNOWN
Requires-Python: >=3.8
Requires-Dist: streamlit (>=1.36.0)
